three/__init__.py
three/constants.py
three/camera/__init__.py
three/camera/base.py
three/camera/perspective_camera.py
three/controls/__init__.py
three/controls/orbit_controls.py
three/controls/ui_event.py
three/core/__init__.py
three/core/buffer_attribute.py
three/core/event.py
three/core/event_dispatcher.py
three/core/geometry.py
three/core/id_provider.py
three/core/inter_leaved_buffer.py
three/core/inter_leaved_buffer_attribute.py
three/core/layers.py
three/core/object3d.py
three/core/ray_caster.py
three/geometries/__init__.py
three/geometries/box_geometry.py
three/geometries/circle_geometry.py
three/geometries/cylinder_geometry.py
three/helpers/__init__.py
three/helpers/axes_helper.py
three/helpers/skeleton_helper.py
three/lights/__init__.py
three/lights/ambient_light.py
three/lights/light.py
three/lights/light_shadow.py
three/lights/point_light.py
three/lights/point_light_shadow.py
three/materials/__init__.py
three/materials/line_basic_material.py
three/materials/material.py
three/materials/mesh_basic_material.py
three/materials/mesh_normal_material.py
three/materials/mesh_standard_material.py
three/materials/points_material.py
three/materials/shader_material.py
three/math/__init__.py
three/math/box2.py
three/math/box3.py
three/math/color.py
three/math/color_management.py
three/math/cylindrical.py
three/math/euler.py
three/math/frustum.py
three/math/interpolant.py
three/math/line3.py
three/math/math_utils.py
three/math/matrix3.py
three/math/matrix4.py
three/math/plane.py
three/math/quaternion.py
three/math/ray.py
three/math/sphere.py
three/math/spherical.py
three/math/sphericalHarmonic3.py
three/math/triangle.py
three/math/vector2.py
three/math/vector3.py
three/math/vector4.py
three/objects/__init__.py
three/objects/bone.py
three/objects/group.py
three/objects/line.py
three/objects/line_segments.py
three/objects/mesh.py
three/objects/scene.py
three/objects/skeleton.py
three/objects/skinned_mesh.py
three/renderer/__init__.py
three/renderer/render_target.py
three_py-0.0.2.dist-info/LICENSE
three_py-0.0.2.dist-info/METADATA
three_py-0.0.2.dist-info/WHEEL
three_py-0.0.2.dist-info/top_level.txt
three_py-0.0.2.dist-info/RECORD
