Metadata-Version: 2.1
Name: three-py
Version: 0.0.2
Summary: A Python render engine like threejs
Home-page: https://github.com/panxinmiao/three-py
Author: Pan Xinmiao
Author-email: pan_xinmiao@163.com
License: MIT
Platform: UNKNOWN
Classifier: Development Status :: 2 - Pre-Alpha
Classifier: Intended Audience :: Developers
Classifier: License :: OSI Approved :: MIT License
Classifier: Programming Language :: Python :: 3
Classifier: Topic :: Software Development :: Libraries :: Python Modules
Classifier: Topic :: Scientific/Engineering :: Visualization
Requires-Python: >=3.7.0
License-File: LICENSE
Requires-Dist: wgpu (<0.9.0,>=0.8.0)
